evan_tools/__init__.py
evan_tools/config/README.md
evan_tools/config/__init__.py
evan_tools/config/main.py
evan_tools/config/concurrency/__init__.py
evan_tools/config/concurrency/rw_lock.py
evan_tools/config/core/__init__.py
evan_tools/config/core/cache.py
evan_tools/config/core/manager.py
evan_tools/config/core/merger.py
evan_tools/config/core/reload_controller.py
evan_tools/config/core/source.py
evan_tools/config/sources/__init__.py
evan_tools/config/sources/directory_source.py
evan_tools/config/sources/yaml_source.py
evan_tools/file/__init__.py
evan_tools/file/collector.py
evan_tools/file/config.py
evan_tools/file/filters.py
evan_tools/file/gatherer.py
evan_tools/file/main.py
evan_tools/file/sorting.py
evan_tools/importer/__init__.py
evan_tools/importer/main.py
evan_tools/md5/__init__.py
evan_tools/md5/api.py
evan_tools/md5/calculator_base.py
evan_tools/md5/calculator_full.py
evan_tools/md5/calculator_sparse.py
evan_tools/md5/config.py
evan_tools/md5/exceptions.py
evan_tools/md5/main.py
evan_tools/md5/result.py
evan_tools/registry/README.md
evan_tools/registry/__init__.py
evan_tools/registry/main.py
evan_tools/registry/dashboard/__init__.py
evan_tools/registry/dashboard/aggregator.py
evan_tools/registry/dashboard/dashboard.py
evan_tools/registry/dashboard/formatter.py
evan_tools/registry/discovery/__init__.py
evan_tools/registry/discovery/index.py
evan_tools/registry/discovery/inspector.py
evan_tools/registry/discovery/metadata.py
evan_tools/registry/storage/__init__.py
evan_tools/registry/storage/memory_store.py
evan_tools/registry/tracking/__init__.py
evan_tools/registry/tracking/models.py
evan_tools/registry/tracking/monitor.py
evan_tools/registry/tracking/tracker.py
evan_tools/setup/__init__.py
evan_tools/setup/main.py
evan_tools/time/__init__.py
evan_tools/time/main.py
evan_tools/tui/__init__.py
evan_tools/tui/example.py
evan_tools/tui/main.py
evan_tools/zip/__init__.py
evan_tools/zip/check.py
evan_tools/zip/unzip.py
evan_tools-0.3.9.dist-info/METADATA
evan_tools-0.3.9.dist-info/WHEEL
evan_tools-0.3.9.dist-info/RECORD
