Metadata-Version: 2.4
Name: evan-tools
Version: 0.3.9
Summary: It's a set of tools for Evan's development.
Author-email: Evan <evanstonlaw555@gmail.com>, Evan <kaluoshilong@qq.com>
Requires-Python: >=3.11
Requires-Dist: humanize>=4.14.0
Requires-Dist: py7zr>=1.1.0
Requires-Dist: pydash>=8.0.5
Requires-Dist: pyyaml>=6.0.3
Requires-Dist: typer>=0.20.0
